prevail_operations/__init__.py
prevail_operations/testFunctions.py
prevail_operations/api_handlers/__init__.py
prevail_operations/api_handlers/flxpoint_api_endpoints.py
prevail_operations/api_handlers/flxpoint_api_handler.py
prevail_operations/api_handlers/kinsey_api_endpoints.py
prevail_operations/api_handlers/kinsey_api_handler.py
prevail_operations/api_handlers/topdawg_api_endpoints.py
prevail_operations/api_handlers/topdawg_api_handler.py
prevail_operations/business_operations/__init__.py
prevail_operations/business_operations/business_operations_handler.py
prevail_operations/data_processing/__init__.py
prevail_operations/data_processing/data_processing.py
prevail_operations/error_handling/__init__.py
prevail_operations/error_handling/error_handling.py
prevail_operations/non_api_handlers/__init__.py
prevail_operations/non_api_handlers/csv_handler.py
prevail_operations/non_api_handlers/email_handler.py
prevail_operations-0.1.dist-info/METADATA
prevail_operations-0.1.dist-info/WHEEL
prevail_operations-0.1.dist-info/top_level.txt
prevail_operations-0.1.dist-info/RECORD
